py_device_detector-0.1.0.dist-info/METADATA
py_device_detector-0.1.0.dist-info/WHEEL
py_device_detector/__init__.py
py_device_detector/__init__.pyi
py_device_detector/py.typed
py_device_detector/py_device_detector.pypy39-pp73-s390x-linux-gnu.so
py_device_detector-0.1.0.dist-info/RECORD
