Metadata-Version: 2.3
Name: py-device-detector
Version: 0.1.0
Classifier: Programming Language :: Rust
Classifier: Programming Language :: Python :: Implementation :: CPython
Classifier: Programming Language :: Python :: Implementation :: PyPy
Classifier: License :: OSI Approved :: GNU Library or Lesser General Public License (LGPL)
Requires-Python: >=3.8
